docker_compose_reloaded/__init__.py
docker_compose_reloaded-0.1.dist-info/LICENSE
docker_compose_reloaded-0.1.dist-info/METADATA
docker_compose_reloaded-0.1.dist-info/WHEEL
docker_compose_reloaded-0.1.dist-info/entry_points.txt
docker_compose_reloaded-0.1.dist-info/top_level.txt
docker_compose_reloaded-0.1.dist-info/RECORD
