Metadata-Version: 2.1
Name: docker-compose-reloaded
Version: 0.1
Summary: A python CLI tool to update stacks on event triggers
Author: TheClockTwister
License-File: LICENSE
Requires-Dist: click
Requires-Dist: colorama
Requires-Dist: paho-mqtt
